ACKNOWLEDGEMENTS
CHANGES
INSTALL
KNOWN_BUGS
LICENSE
MANIFEST.in
README.md
TODO
setup.py
version
doc/gendoc.py
doc/html/default.css
doc/html/html4css1.css
doc/html/pygments.css
doc/html/images/compat_wx.py
doc/html/images/convert_images.py
doc/html/images/img2img.py
doc/html/images/img2py.py
doc/src/analysis.txt
doc/src/args.txt
doc/src/binarization.txt
doc/src/classes.txt
doc/src/classification.txt
doc/src/classify.txt
doc/src/color.txt
doc/src/combine.txt
doc/src/conversion.txt
doc/src/corelation.txt
doc/src/default.css
doc/src/deformations.txt
doc/src/dimension_types.txt
doc/src/directory_hierarchy.txt
doc/src/displaying.txt
doc/src/draw.txt
doc/src/edge.txt
doc/src/externallibraries.txt
doc/src/features.txt
doc/src/file.txt
doc/src/filter.txt
doc/src/ga_optimization.txt
doc/src/gamera.core.ImageData.txt
doc/src/gamera.core.ImageInfo.txt
doc/src/gamera.core.RGBPixel.txt
doc/src/geometry.txt
doc/src/graph.txt
doc/src/gui.txt
doc/src/html4css1.css
doc/src/image_api.txt
doc/src/image_types.txt
doc/src/index.txt
doc/src/install.txt
doc/src/kdtree.txt
doc/src/list.txt
doc/src/major_changes_3x.txt
doc/src/matplotlib_support.txt
doc/src/migration_guide.txt
doc/src/morphology.txt
doc/src/overriding_knn_features.txt
doc/src/overview.txt
doc/src/pagesegmentation.txt
doc/src/plugins.txt
doc/src/plugins_custom_types.txt
doc/src/relational.txt
doc/src/runlength.txt
doc/src/script.txt
doc/src/segmentation.txt
doc/src/thinning.txt
doc/src/training_tutorial.txt
doc/src/transformation.txt
doc/src/unit_testing.txt
doc/src/utility.txt
doc/src/writing_plugins.txt
doc/src/writing_toolkits.txt
doc/src/xml.txt
doc/src/xml_format.txt
doc/src/images/1bit_png.png
doc/src/images/arguments_dialog.png
doc/src/images/arguments_example.png
doc/src/images/autoclassified_color.png
doc/src/images/autocompletion.png
doc/src/images/biollante_results_sub.png
doc/src/images/biollante_settings.png
doc/src/images/biollante_status_sub.png
doc/src/images/classifier_window.png
doc/src/images/color_ccs.png
gamera.egg-info/PKG-INFO
gamera.egg-info/SOURCES.txt
gamera.egg-info/dependency_links.txt
gamera.egg-info/entry_points.txt
gamera.egg-info/top_level.txt
