Metadata-Version: 2.1
Name: gamera
Version: 4.1.0
Summary: Gamera is a framework for building document analysis applications. It is not a packaged document recognition system, but a toolkit for building document image recognition systems.
Home-page: https://gamera.sourceforge.net/
Author: Michael Droettboom and Christoph Dalitz
License: GNU GENERAL PUBLIC LICENSE Version 2
Project-URL: Documentation, https://gamera.informatik.hsnr.de/docs/gamera-docs/
Project-URL: Source, https://github.com/hsnr-gamera/gamera-4
Platform: UNKNOWN
Classifier: Development Status :: 5 - Production/Stable
Classifier: Intended Audience :: Developers
Classifier: License :: OSI Approved :: GNU General Public License v2 (GPLv2)
Classifier: Operating System :: OS Independent
Classifier: Programming Language :: Python
Classifier: Programming Language :: Python :: 3
Classifier: Programming Language :: Python :: 3 :: Only
Classifier: Topic :: Text Processing
Classifier: Topic :: Multimedia :: Graphics
Requires-Python: >=3.5
